{
  "_class": "symbolInstance",
  "booleanOperation": 0,
  "clippingMaskMode": 0,
  "do_objectID": "DFC92FE2-807D-423A-81A2-5577AA745F04",
  "exportOptions": {
    "_class": "exportOptions",
    "exportFormats": [
    ],
    "includedLayerIds": [
    ],
    "layerOptions": 0,
    "shouldTrim": false
  },
  "frame": {
    "_class": "rect",
    "constrainProportions": false,
    "height": 50,
    "width": 170,
    "x": 921,
    "y": 189
  },
  "hasClippingMask": false,
  "horizontalSpacing": 0,
  "isFixedToViewport": false,
  "isFlippedHorizontal": false,
  "isFlippedVertical": false,
  "isLocked": false,
  "isVisible": true,
  "layerListExpandedType": 0,
  "name": "CTA button/1.1static Copy 23",
  "nameIsFixed": false,
  "originalObjectID": "352C3859-5F5E-4EB0-AB49-2B001F6473F7",
  "overrideValues": [
    {
      "_class": "overrideValue",
      "overrideName": "6124BE72-6EF8-4510-BBF5-1F2AE4BCBC6D_stringValue",
      "value": "Focus"
    },
    {
      "_class": "overrideValue",
      "overrideName": "7EDD61CF-E9DB-4194-8F3E-D12D4FAFD1E0_layerStyle",
      "value": "3C0F80A0-CE7B-41EA-983C-515313D5B709"
    }
  ],
  "resizingConstraint": 63,
  "resizingType": 0,
  "rotation": 0,
  "scale": 1,
  "shouldBreakMaskChain": false,
  "style": {
    "_class": "style",
    "blur": {
      "_class": "blur",
      "center": "{0.5, 0.5}",
      "isEnabled": false,
      "motionAngle": 0,
      "radius": 10,
      "saturation": 1,
      "type": 0
    },
    "borderOptions": {
      "_class": "borderOptions",
      "dashPattern": [
      ],
      "isEnabled": true,
      "lineCapStyle": 0,
      "lineJoinStyle": 0
    },
    "borders": [
    ],
    "colorControls": {
      "_class": "colorControls",
      "brightness": 0,
      "contrast": 1,
      "hue": 0,
      "isEnabled": true,
      "saturation": 1
    },
    "contextSettings": {
      "_class": "graphicsContextSettings",
      "blendMode": 0,
      "opacity": 1
    },
    "do_objectID": "13A6B89B-5154-430D-925D-F1C1F3CF0E4E",
    "endMarkerType": 0,
    "fills": [
    ],
    "innerShadows": [
    ],
    "miterLimit": 10,
    "shadows": [
    ],
    "startMarkerType": 0,
    "windingRule": 1
  },
  "symbolID": "2C86DC46-B56C-49C4-B94D-9AE056FF32A6",
  "verticalSpacing": 0
}