{
  "_class": "symbolMaster",
  "allowsOverrides": true,
  "backgroundColor": {
    "_class": "color",
    "alpha": 1,
    "blue": 1,
    "green": 1,
    "red": 1
  },
  "booleanOperation": -1,
  "changeIdentifier": 1933,
  "clippingMaskMode": 0,
  "do_objectID": "AB39551D-7205-4B04-94FE-3CDCDF900894",
  "exportOptions": {
    "_class": "exportOptions",
    "exportFormats": [
    ],
    "includedLayerIds": [
    ],
    "layerOptions": 0,
    "shouldTrim": false
  },
  "frame": {
    "_class": "rect",
    "constrainProportions": false,
    "height": 51,
    "width": 1140,
    "x": 228529,
    "y": -9039
  },
  "groupLayout": {
    "_class": "MSImmutableFreeformGroupLayout"
  },
  "hasBackgroundColor": false,
  "hasClickThrough": true,
  "hasClippingMask": false,
  "horizontalRulerData": {
    "_class": "rulerData",
    "base": 0,
    "guides": [
    ]
  },
  "includeBackgroundColorInExport": true,
  "includeBackgroundColorInInstance": false,
  "includeInCloudUpload": true,
  "isFixedToViewport": false,
  "isFlippedHorizontal": false,
  "isFlippedVertical": false,
  "isFlowHome": false,
  "isLocked": false,
  "isVisible": true,
  "layerListExpandedType": 2,
  "layers": [
    {
      "class": "rectangle",
      "id": "B193589F-D3EA-4066-B3F4-EC9D1840E4F5"
    },
    {
      "class": "symbolInstance",
      "id": "B585F2F9-4FDC-4754-89FA-378F284217BE"
    },
    {
      "class": "text",
      "id": "D7FA4AF6-B2F5-49D6-94C4-F18B0B5B6559"
    },
    {
      "class": "text",
      "id": "D6A23FAE-E3E5-46B9-80D3-E0F54B5E4B0D"
    },
    {
      "class": "symbolInstance",
      "id": "66E7CD8A-D546-4051-A10E-BF09533CF497"
    },
    {
      "class": "symbolInstance",
      "id": "46121C09-5B25-4CCD-9843-30AD602B0BAD"
    }
  ],
  "name": "Alerts/Hint/success-info",
  "nameIsFixed": true,
  "overrideProperties": [
    {
      "_class": "MSImmutableOverrideProperty",
      "canOverride": true,
      "overrideName": "D6A23FAE-E3E5-46B9-80D3-E0F54B5E4B0D_stringValue"
    },
    {
      "_class": "MSImmutableOverrideProperty",
      "canOverride": true,
      "overrideName": "46121C09-5B25-4CCD-9843-30AD602B0BAD_symbolID"
    },
    {
      "_class": "MSImmutableOverrideProperty",
      "canOverride": true,
      "overrideName": "B193589F-D3EA-4066-B3F4-EC9D1840E4F5_layerStyle"
    },
    {
      "_class": "MSImmutableOverrideProperty",
      "canOverride": true,
      "overrideName": "D7FA4AF6-B2F5-49D6-94C4-F18B0B5B6559_textStyle"
    },
    {
      "_class": "MSImmutableOverrideProperty",
      "canOverride": true,
      "overrideName": "D7FA4AF6-B2F5-49D6-94C4-F18B0B5B6559_stringValue"
    },
    {
      "_class": "MSImmutableOverrideProperty",
      "canOverride": true,
      "overrideName": "B585F2F9-4FDC-4754-89FA-378F284217BE_symbolID"
    },
    {
      "_class": "MSImmutableOverrideProperty",
      "canOverride": true,
      "overrideName": "66E7CD8A-D546-4051-A10E-BF09533CF497_symbolID"
    }
  ],
  "presetDictionary": {
  },
  "resizesContent": true,
  "resizingConstraint": 63,
  "resizingType": 0,
  "rotation": 0,
  "shouldBreakMaskChain": true,
  "style": {
    "_class": "style",
    "blur": {
      "_class": "blur",
      "center": "{0.5, 0.5}",
      "isEnabled": false,
      "motionAngle": 0,
      "radius": 10,
      "saturation": 1,
      "type": 0
    },
    "borderOptions": {
      "_class": "borderOptions",
      "dashPattern": [
      ],
      "isEnabled": true,
      "lineCapStyle": 0,
      "lineJoinStyle": 0
    },
    "borders": [
    ],
    "colorControls": {
      "_class": "colorControls",
      "brightness": 0,
      "contrast": 1,
      "hue": 0,
      "isEnabled": true,
      "saturation": 1
    },
    "contextSettings": {
      "_class": "graphicsContextSettings",
      "blendMode": 0,
      "opacity": 1
    },
    "do_objectID": "2B930B76-0467-4144-B8BD-7BB3C282E864",
    "endMarkerType": 0,
    "fills": [
    ],
    "innerShadows": [
    ],
    "miterLimit": 10,
    "shadows": [
    ],
    "startMarkerType": 0,
    "windingRule": 1
  },
  "symbolID": "E74AABF8-5E49-46B6-87DC-A44328AEBE2D",
  "verticalRulerData": {
    "_class": "rulerData",
    "base": 0,
    "guides": [
    ]
  }
}