{
  "_class": "symbolMaster",
  "allowsOverrides": true,
  "backgroundColor": {
    "_class": "color",
    "alpha": 1,
    "blue": 0,
    "green": 0,
    "red": 0
  },
  "booleanOperation": 0,
  "changeIdentifier": 3145,
  "clippingMaskMode": 0,
  "do_objectID": "1BBDCB73-AE98-41EC-986C-B954BEEE196A",
  "exportOptions": {
    "_class": "exportOptions",
    "exportFormats": [
    ],
    "includedLayerIds": [
    ],
    "layerOptions": 0,
    "shouldTrim": false
  },
  "frame": {
    "_class": "rect",
    "constrainProportions": false,
    "height": 34,
    "width": 66,
    "x": 224047,
    "y": -13031
  },
  "groupLayout": {
    "_class": "MSImmutableInferredGroupLayout",
    "axis": 0,
    "layoutAnchor": 1,
    "maxSize": 0,
    "minSize": 0
  },
  "hasBackgroundColor": true,
  "hasClickThrough": true,
  "hasClippingMask": false,
  "horizontalRulerData": {
    "_class": "rulerData",
    "base": 0,
    "guides": [
    ]
  },
  "includeBackgroundColorInExport": true,
  "includeBackgroundColorInInstance": false,
  "includeInCloudUpload": true,
  "isFixedToViewport": false,
  "isFlippedHorizontal": false,
  "isFlippedVertical": false,
  "isFlowHome": false,
  "isLocked": false,
  "isVisible": true,
  "layerListExpandedType": 2,
  "layers": [
    {
      "class": "rectangle",
      "id": "BDD7CC36-14AC-4071-9485-7A232421C82D"
    },
    {
      "class": "rectangle",
      "id": "CA4280B4-BEAD-4B46-9099-F5B50EF36E5C"
    },
    {
      "class": "text",
      "id": "98E62C31-A765-4092-8BE3-4F3FE549EF20"
    }
  ],
  "name": "Buttons/Dark Outline/Small/.Simple/pressed",
  "nameIsFixed": true,
  "originalObjectID": "60B5D717-69A4-4D31-91F2-6E91D8BD8137",
  "overrideProperties": [
    {
      "_class": "MSImmutableOverrideProperty",
      "canOverride": true,
      "overrideName": "BDD7CC36-14AC-4071-9485-7A232421C82D_layerStyle"
    },
    {
      "_class": "MSImmutableOverrideProperty",
      "canOverride": true,
      "overrideName": "98E62C31-A765-4092-8BE3-4F3FE549EF20_stringValue"
    },
    {
      "_class": "MSImmutableOverrideProperty",
      "canOverride": true,
      "overrideName": "98E62C31-A765-4092-8BE3-4F3FE549EF20_textStyle"
    },
    {
      "_class": "MSImmutableOverrideProperty",
      "canOverride": true,
      "overrideName": "CA4280B4-BEAD-4B46-9099-F5B50EF36E5C_layerStyle"
    }
  ],
  "presetDictionary": {
  },
  "resizesContent": true,
  "resizingConstraint": 63,
  "resizingType": 0,
  "rotation": 0,
  "shouldBreakMaskChain": true,
  "style": {
    "_class": "style",
    "blur": {
      "_class": "blur",
      "center": "{0.5, 0.5}",
      "isEnabled": false,
      "motionAngle": 0,
      "radius": 10,
      "saturation": 1,
      "type": 0
    },
    "borderOptions": {
      "_class": "borderOptions",
      "dashPattern": [
      ],
      "isEnabled": true,
      "lineCapStyle": 0,
      "lineJoinStyle": 0
    },
    "borders": [
    ],
    "colorControls": {
      "_class": "colorControls",
      "brightness": 0,
      "contrast": 1,
      "hue": 0,
      "isEnabled": true,
      "saturation": 1
    },
    "contextSettings": {
      "_class": "graphicsContextSettings",
      "blendMode": 0,
      "opacity": 1
    },
    "do_objectID": "83662CC5-C6CE-409D-BA1F-F5A2B5EC3DA7",
    "endMarkerType": 0,
    "fills": [
    ],
    "innerShadows": [
    ],
    "miterLimit": 10,
    "shadows": [
    ],
    "startMarkerType": 0,
    "windingRule": 1
  },
  "symbolID": "C20B0A09-6042-41D7-BE37-856EF2AA8666",
  "verticalRulerData": {
    "_class": "rulerData",
    "base": 0,
    "guides": [
    ]
  }
}