{
  "_class": "group",
  "booleanOperation": -1,
  "clippingMaskMode": 0,
  "do_objectID": "D4C38D11-572F-436C-9B0D-5CBEE76D7865",
  "exportOptions": {
    "_class": "exportOptions",
    "exportFormats": [
    ],
    "includedLayerIds": [
    ],
    "layerOptions": 0,
    "shouldTrim": false
  },
  "frame": {
    "_class": "rect",
    "constrainProportions": false,
    "height": 180,
    "width": 294,
    "x": 0,
    "y": 0
  },
  "groupLayout": {
    "_class": "MSImmutableFreeformGroupLayout"
  },
  "hasClickThrough": false,
  "hasClippingMask": false,
  "isFixedToViewport": false,
  "isFlippedHorizontal": false,
  "isFlippedVertical": false,
  "isLocked": false,
  "isVisible": true,
  "layerListExpandedType": 2,
  "layers": [
    {
      "class": "rectangle",
      "id": "7BCF2751-C90E-412D-ABDE-A7FC1A93DF26"
    },
    {
      "class": "text",
      "id": "6C78202E-8E2F-4BBF-B8BB-5F6658CEA376"
    },
    {
      "class": "text",
      "id": "7AC87348-4507-4620-8CCB-0E6604AE41E4"
    },
    {
      "class": "text",
      "id": "3C9F38BF-53B2-4512-8C37-BF46E8F1D170"
    },
    {
      "class": "text",
      "id": "E646796F-5626-4341-A359-A8797C6BC877"
    },
    {
      "class": "text",
      "id": "8174670F-8C9C-43D7-8BDA-EE646A2659A5"
    },
    {
      "class": "text",
      "id": "F378C602-1FB7-49C2-92F9-08DE0953FB73"
    },
    {
      "class": "text",
      "id": "EC813E6C-7404-4E96-B055-AE603C72ECAE"
    }
  ],
  "name": "Group 2 Copy 103",
  "nameIsFixed": false,
  "resizingConstraint": 63,
  "resizingType": 0,
  "rotation": 0,
  "shouldBreakMaskChain": false,
  "style": {
    "_class": "style",
    "blur": {
      "_class": "blur",
      "center": "{0.5, 0.5}",
      "isEnabled": false,
      "motionAngle": 0,
      "radius": 10,
      "saturation": 1,
      "type": 0
    },
    "borderOptions": {
      "_class": "borderOptions",
      "dashPattern": [
      ],
      "isEnabled": true,
      "lineCapStyle": 0,
      "lineJoinStyle": 0
    },
    "borders": [
    ],
    "colorControls": {
      "_class": "colorControls",
      "brightness": 0,
      "contrast": 1,
      "hue": 0,
      "isEnabled": true,
      "saturation": 1
    },
    "contextSettings": {
      "_class": "graphicsContextSettings",
      "blendMode": 0,
      "opacity": 1
    },
    "do_objectID": "B21CCEF6-FB98-44D7-A7A9-E9B5ADF40657",
    "endMarkerType": 0,
    "fills": [
      {
        "_class": "fill",
        "color": {
          "_class": "color",
          "alpha": 1,
          "blue": 0.2980392156862745,
          "green": 0.2980392156862745,
          "red": 0.2980392156862745
        },
        "contextSettings": {
          "_class": "graphicsContextSettings",
          "blendMode": 0,
          "opacity": 1
        },
        "fillType": 0,
        "gradient": {
          "_class": "gradient",
          "elipseLength": 0,
          "from": "{0.5, 0}",
          "gradientType": 0,
          "stops": [
            {
              "_class": "gradientStop",
              "color": {
                "_class": "color",
                "alpha": 1,
                "blue": 0.2980392156862745,
                "green": 0.2980392156862745,
                "red": 0.2980392156862745
              },
              "position": 0
            },
            {
              "_class": "gradientStop",
              "color": {
                "_class": "color",
                "alpha": 0.5,
                "blue": 0,
                "green": 0,
                "red": 0
              },
              "position": 1
            }
          ],
          "to": "{0.5, 1}"
        },
        "isEnabled": true,
        "noiseIndex": 0,
        "noiseIntensity": 0,
        "patternFillType": 1,
        "patternTileScale": 1
      },
      {
        "_class": "fill",
        "color": {
          "_class": "color",
          "alpha": 0.4,
          "blue": 0,
          "green": 0,
          "red": 0
        },
        "contextSettings": {
          "_class": "graphicsContextSettings",
          "blendMode": 2,
          "opacity": 1
        },
        "fillType": 0,
        "gradient": {
          "_class": "gradient",
          "elipseLength": 0,
          "from": "{0.5, 0}",
          "gradientType": 0,
          "stops": [
            {
              "_class": "gradientStop",
              "color": {
                "_class": "color",
                "alpha": 0.5,
                "blue": 1,
                "green": 1,
                "red": 1
              },
              "position": 0
            },
            {
              "_class": "gradientStop",
              "color": {
                "_class": "color",
                "alpha": 0.5,
                "blue": 0,
                "green": 0,
                "red": 0
              },
              "position": 1
            }
          ],
          "to": "{0.5, 1}"
        },
        "isEnabled": true,
        "noiseIndex": 0,
        "noiseIntensity": 0,
        "patternFillType": 1,
        "patternTileScale": 1
      }
    ],
    "innerShadows": [
    ],
    "miterLimit": 10,
    "shadows": [
    ],
    "startMarkerType": 0,
    "windingRule": 1
  }
}